oscontainer/__init__.py
oscontainer/cgroup_subsystem.py
oscontainer/cgroup_v1_subsystem.py
oscontainer/cgroup_v2_subsystem.py
oscontainer/cgroups.py
oscontainer/constants.py
oscontainer/errors.py
oscontainer/os_container.py
oscontainer/scanf.py
oscontainer/utils.py
oscontainer-1.0.2.dist-info/LICENSE
oscontainer-1.0.2.dist-info/METADATA
oscontainer-1.0.2.dist-info/WHEEL
oscontainer-1.0.2.dist-info/top_level.txt
oscontainer-1.0.2.dist-info/RECORD
