Metadata-Version: 2.1
Name: oscontainer
Version: 1.0.2
Summary: The small Python library to read resources available for Linux OS container.
Home-page: https://github.com/yaricom/oscontainer
Author: Iaroslav Omelianenko
Author-email: yaric_mail@yahoo.com
License: UNKNOWN
Project-URL: Docs, https://github.com/yaricom/oscontainer
Platform: UNKNOWN
Classifier: Programming Language :: Python
Classifier: Programming Language :: Python :: 2
Classifier: Programming Language :: Python :: 2.7
Classifier: Programming Language :: Python :: 3
Classifier: Programming Language :: Python :: 3.5
Classifier: Programming Language :: Python :: 3.6
Classifier: Programming Language :: Python :: 3.7
Classifier: Programming Language :: Python :: 3.8
Classifier: Programming Language :: Python :: 3.9
Classifier: Programming Language :: Python :: 3.10
Classifier: License :: OSI Approved :: MIT License
Classifier: Operating System :: POSIX :: Linux
Requires-Python: !=3.0.*,!=3.1.*,!=3.2.*,!=3.3.*,!=3.4.*,>=2.7
License-File: LICENSE
